rickrollprinter/__init__.py
rickrollprinter/never_gonna_give_you_up.mp3
rickrollprinter/rickrollprinter.py
rickrollprinter-0.1.3.dist-info/LICENSE
rickrollprinter-0.1.3.dist-info/METADATA
rickrollprinter-0.1.3.dist-info/WHEEL
rickrollprinter-0.1.3.dist-info/top_level.txt
rickrollprinter-0.1.3.dist-info/RECORD
