Metadata-Version: 2.1
Name: rickrollprinter
Version: 0.1.3
Summary: A Python package that prints Rickroll lyrics and plays the song.
Home-page: https://github.com/jayounghoyos/rickrollprinter
Author: Juan Andrés Young Hoyos
Author-email: juanandresyounghoyos@gmail.com
Classifier: Programming Language :: Python :: 3
Classifier: License :: OSI Approved :: MIT License
Classifier: Operating System :: OS Independent
Requires-Python: >=3.6
License-File: LICENSE
Requires-Dist: pygame
